SparkGraphxYuanmaFenxi/README.md
SparkGraphxYuanmaFenxi/__init__.py
SparkGraphxYuanmaFenxi/__main__.py
SparkGraphxYuanmaFenxi/file.epub
SparkGraphxYuanmaFenxi/index.html
SparkGraphxYuanmaFenxi/css/__init__.py
SparkGraphxYuanmaFenxi/css/annotations.css
SparkGraphxYuanmaFenxi/css/main.css
SparkGraphxYuanmaFenxi/css/normalize.css
SparkGraphxYuanmaFenxi/css/popup.css
SparkGraphxYuanmaFenxi/font/__init__.py
SparkGraphxYuanmaFenxi/font/fontello.eot
SparkGraphxYuanmaFenxi/font/fontello.svg
SparkGraphxYuanmaFenxi/font/fontello.ttf
SparkGraphxYuanmaFenxi/font/fontello.woff
SparkGraphxYuanmaFenxi/img/__init__.py
SparkGraphxYuanmaFenxi/img/annotator-glyph-sprite.png
SparkGraphxYuanmaFenxi/img/annotator-icon-sprite.png
SparkGraphxYuanmaFenxi/img/apple-touch-icon.png
SparkGraphxYuanmaFenxi/img/cancelfullscreen.png
SparkGraphxYuanmaFenxi/img/close.png
SparkGraphxYuanmaFenxi/img/fullscreen.png
SparkGraphxYuanmaFenxi/img/loader.gif
SparkGraphxYuanmaFenxi/img/menu-icon.png
SparkGraphxYuanmaFenxi/img/save.png
SparkGraphxYuanmaFenxi/img/saved.png
SparkGraphxYuanmaFenxi/img/settings-s.png
SparkGraphxYuanmaFenxi/img/settings.png
SparkGraphxYuanmaFenxi/img/star.png
SparkGraphxYuanmaFenxi/js/__init__.py
SparkGraphxYuanmaFenxi/js/epub.js
SparkGraphxYuanmaFenxi/js/epub.min.js
SparkGraphxYuanmaFenxi/js/epub.min.map
SparkGraphxYuanmaFenxi/js/hooks.min.js
SparkGraphxYuanmaFenxi/js/hooks.min.map
SparkGraphxYuanmaFenxi/js/reader.js
SparkGraphxYuanmaFenxi/js/reader.js.map
SparkGraphxYuanmaFenxi/js/reader.min.js
SparkGraphxYuanmaFenxi/js/reader.min.map
SparkGraphxYuanmaFenxi/js/hooks/__init__.py
SparkGraphxYuanmaFenxi/js/hooks/extensions/__init__.py
SparkGraphxYuanmaFenxi/js/hooks/extensions/highlight.js
SparkGraphxYuanmaFenxi/js/libs/__init__.py
SparkGraphxYuanmaFenxi/js/libs/jquery.min.js
SparkGraphxYuanmaFenxi/js/libs/localforage.min.js
SparkGraphxYuanmaFenxi/js/libs/screenfull.js
SparkGraphxYuanmaFenxi/js/libs/screenfull.min.js
SparkGraphxYuanmaFenxi/js/libs/zip.min.js
spark_graphx_yuanma_fenxi-2024.3.3.0.dist-info/METADATA
spark_graphx_yuanma_fenxi-2024.3.3.0.dist-info/WHEEL
spark_graphx_yuanma_fenxi-2024.3.3.0.dist-info/entry_points.txt
spark_graphx_yuanma_fenxi-2024.3.3.0.dist-info/top_level.txt
spark_graphx_yuanma_fenxi-2024.3.3.0.dist-info/RECORD
